jupyterlab_symbol_sidebar/__init__.py
jupyterlab_symbol_sidebar/_version.py
jupyterlab_symbol_sidebar-0.1.3.data/data/share/jupyter/labextensions/jupyterlab-symbol-sidebar/build_log.json
jupyterlab_symbol_sidebar-0.1.3.data/data/share/jupyter/labextensions/jupyterlab-symbol-sidebar/package.json
jupyterlab_symbol_sidebar-0.1.3.data/data/share/jupyter/labextensions/jupyterlab-symbol-sidebar/static/lib_index_js.b1052f4fedf8040af529.js
jupyterlab_symbol_sidebar-0.1.3.data/data/share/jupyter/labextensions/jupyterlab-symbol-sidebar/static/lib_index_js.b1052f4fedf8040af529.js.map
jupyterlab_symbol_sidebar-0.1.3.data/data/share/jupyter/labextensions/jupyterlab-symbol-sidebar/static/lib_index_js.d9f8336d88f6d2643dc4.js
jupyterlab_symbol_sidebar-0.1.3.data/data/share/jupyter/labextensions/jupyterlab-symbol-sidebar/static/lib_index_js.d9f8336d88f6d2643dc4.js.map
jupyterlab_symbol_sidebar-0.1.3.data/data/share/jupyter/labextensions/jupyterlab-symbol-sidebar/static/remoteEntry.16102efa3beef8274f10.js.map
jupyterlab_symbol_sidebar-0.1.3.data/data/share/jupyter/labextensions/jupyterlab-symbol-sidebar/static/remoteEntry.5757e84599465c384fc8.js
jupyterlab_symbol_sidebar-0.1.3.data/data/share/jupyter/labextensions/jupyterlab-symbol-sidebar/static/remoteEntry.5757e84599465c384fc8.js.map
jupyterlab_symbol_sidebar-0.1.3.data/data/share/jupyter/labextensions/jupyterlab-symbol-sidebar/static/style.js
jupyterlab_symbol_sidebar-0.1.3.data/data/share/jupyter/labextensions/jupyterlab-symbol-sidebar/static/style_index_js.457fec1e42312677f0bc.js
jupyterlab_symbol_sidebar-0.1.3.data/data/share/jupyter/labextensions/jupyterlab-symbol-sidebar/static/style_index_js.457fec1e42312677f0bc.js.map
jupyterlab_symbol_sidebar-0.1.3.data/data/share/jupyter/labextensions/jupyterlab-symbol-sidebar/static/vendors-node_modules_css-loader_dist_runtime_api_js-node_modules_css-loader_dist_runtime_cssW-72eba1.05da8e577591745ac94c.js
jupyterlab_symbol_sidebar-0.1.3.dist-info/METADATA
jupyterlab_symbol_sidebar-0.1.3.dist-info/WHEEL
jupyterlab_symbol_sidebar-0.1.3.dist-info/licenses/LICENSE
jupyterlab_symbol_sidebar-0.1.3.dist-info/RECORD
