Metadata-Version: 2.1
Name: jupyterlab_symbol_sidebar
Version: 0.1.3
Summary: Easily copy unicode char into Jupyter Lab
Project-URL: Homepage, https://github.com/KrunkZhou/jupyterlab_symbol_sidebar
Project-URL: Bug Tracker, https://github.com/KrunkZhou/jupyterlab_symbol_sidebar/issues
Project-URL: Repository, https://github.com/KrunkZhou/jupyterlab_symbol_sidebar.git
Author-email: Tianyu Zhou <webmaster@krunk.cn>
License: BSD 3-Clause License
License-File: LICENSE
Classifier: Framework :: Jupyter
Classifier: Framework :: Jupyter :: JupyterLab
Classifier: Framework :: Jupyter :: JupyterLab :: 3
Classifier: Framework :: Jupyter :: JupyterLab :: Extensions
Classifier: Framework :: Jupyter :: JupyterLab :: Extensions :: Prebuilt
Classifier: License :: OSI Approved :: BSD License
Classifier: Programming Language :: Python
Classifier: Programming Language :: Python :: 3
Classifier: Programming Language :: Python :: 3.7
Classifier: Programming Language :: Python :: 3.8
Classifier: Programming Language :: Python :: 3.9
Classifier: Programming Language :: Python :: 3.10
Classifier: Programming Language :: Python :: 3.11
Requires-Python: >=3.7
